spatialflow/__init__.py
spatialflow/builders.py
spatialflow/client.py
spatialflow/exceptions.py
spatialflow/jobs.py
spatialflow/pagination.py
spatialflow/py.typed
spatialflow/resources.py
spatialflow/uploads.py
spatialflow/webhooks.py
spatialflow/_generated/spatialflow_generated/__init__.py
spatialflow/_generated/spatialflow_generated/api_client.py
spatialflow/_generated/spatialflow_generated/api_response.py
spatialflow/_generated/spatialflow_generated/configuration.py
spatialflow/_generated/spatialflow_generated/exceptions.py
spatialflow/_generated/spatialflow_generated/py.typed
spatialflow/_generated/spatialflow_generated/rest.py
spatialflow/_generated/spatialflow_generated/api/__init__.py
spatialflow/_generated/spatialflow_generated/api/account_api.py
spatialflow/_generated/spatialflow_generated/api/admin_api.py
spatialflow/_generated/spatialflow_generated/api/authentication_api.py
spatialflow/_generated/spatialflow_generated/api/billing_api.py
spatialflow/_generated/spatialflow_generated/api/default_api.py
spatialflow/_generated/spatialflow_generated/api/devices_api.py
spatialflow/_generated/spatialflow_generated/api/e2_e_test_api.py
spatialflow/_generated/spatialflow_generated/api/email_api.py
spatialflow/_generated/spatialflow_generated/api/geofences_api.py
spatialflow/_generated/spatialflow_generated/api/gpx_simulator_api.py
spatialflow/_generated/spatialflow_generated/api/integrations_api.py
spatialflow/_generated/spatialflow_generated/api/public_api.py
spatialflow/_generated/spatialflow_generated/api/public_location_ingest_api.py
spatialflow/_generated/spatialflow_generated/api/simulation_center_api.py
spatialflow/_generated/spatialflow_generated/api/storage_api.py
spatialflow/_generated/spatialflow_generated/api/subscriptions_api.py
spatialflow/_generated/spatialflow_generated/api/system_api.py
spatialflow/_generated/spatialflow_generated/api/tiles_api.py
spatialflow/_generated/spatialflow_generated/api/webhooks_api.py
spatialflow-0.2.0.dist-info/METADATA
spatialflow-0.2.0.dist-info/WHEEL
spatialflow-0.2.0.dist-info/licenses/LICENSE
spatialflow-0.2.0.dist-info/RECORD
