Metadata-Version: 2.4
Name: spatialflow
Version: 0.2.0
Summary: Python SDK for SpatialFlow - Real-time geospatial automation platform
Project-URL: Homepage, https://spatialflow.io
Project-URL: Documentation, https://docs.spatialflow.io/sdk/python
Project-URL: Repository, https://github.com/spatialflow-io/spatialflow-python
Project-URL: Issues, https://github.com/spatialflow-io/spatialflow-python/issues
Project-URL: Changelog, https://github.com/spatialflow-io/spatialflow-python/blob/main/CHANGELOG.md
Author-email: SpatialFlow <support@spatialflow.io>
License-Expression: MIT
License-File: LICENSE
Keywords: automation,geofencing,geospatial,location,sdk,spatialflow
Classifier: Development Status :: 3 - Alpha
Classifier: Intended Audience :: Developers
Classifier: License :: OSI Approved :: MIT License
Classifier: Operating System :: OS Independent
Classifier: Programming Language :: Python :: 3
Classifier: Programming Language :: Python :: 3.9
Classifier: Programming Language :: Python :: 3.10
Classifier: Programming Language :: Python :: 3.11
Classifier: Programming Language :: Python :: 3.12
Classifier: Programming Language :: Python :: 3.13
Classifier: Topic :: Scientific/Engineering :: GIS
Classifier: Topic :: Software Development :: Libraries :: Python Modules
Classifier: Typing :: Typed
Requires-Python: >=3.9
Requires-Dist: aiohttp-retry>=2.8.3
Requires-Dist: aiohttp>=3.8.4
Requires-Dist: pydantic>=2.0.0
Requires-Dist: python-dateutil>=2.8.2
Requires-Dist: typing-extensions>=4.7.1
Requires-Dist: urllib3<3.0.0,>=1.25.3
Provides-Extra: dev
Requires-Dist: aioresponses>=0.7.4; extra == 'dev'
Requires-Dist: mypy>=1.0.0; extra == 'dev'
Requires-Dist: pytest-asyncio>=0.21.0; extra == 'dev'
Requires-Dist: pytest-cov>=4.0.0; extra == 'dev'
Requires-Dist: pytest>=7.0.0; extra == 'dev'
Requires-Dist: ruff>=0.1.0; extra == 'dev'
Provides-Extra: docs
Requires-Dist: mkdocs-material>=9.0.0; extra == 'docs'
Requires-Dist: mkdocs>=1.5.0; extra == 'docs'
Requires-Dist: mkdocstrings[python]>=0.24.0; extra == 'docs'
